v2expkg/__init__.py
v2expkg/data.py
v2expkg/models.py
v2expkg/v2ex.py
v2expkg/web.py
v2ex-0.1.0.dist-info/METADATA
v2ex-0.1.0.dist-info/WHEEL
v2ex-0.1.0.dist-info/entry_points.txt
v2ex-0.1.0.dist-info/top_level.txt
v2ex-0.1.0.dist-info/RECORD
