Metadata-Version: 2.4
Name: v2ex
Version: 0.1.0
Summary: V2EX 热门话题终端工具
Author: xiao.xu
Author-email: 
Requires-Python: >=3.7
Requires-Dist: rich
Requires-Dist: prompt_toolkit
Requires-Dist: requests
Requires-Dist: beautifulsoup4
Requires-Dist: lxml
Requires-Dist: paprika
Requires-Dist: markdown-it-py
Requires-Dist: Pygments
Requires-Dist: tabulate
Requires-Dist: typing_extensions
Requires-Dist: urllib3
Requires-Dist: wcwidth
Requires-Dist: certifi
Requires-Dist: charset-normalizer
Requires-Dist: idna
Requires-Dist: mdurl
Requires-Dist: soupsieve
Requires-Dist: bs4
Dynamic: author
Dynamic: requires-dist
Dynamic: requires-python
Dynamic: summary
